Metadata-Version: 2.1
Name: phsutaprofile
Version: 0.0.5
Summary: PhsutaProfile By B1ackmonday
Home-page: https://github.com/B1ackmonday/PhsutaProfile
Author: B1ackmonday
Author-email: joseph_t1904@hotmail.com
License: MIT
Download-URL: https://github.com/B1ackmonday/PhsutaProfile/archive/v0.0.5.zip
Keywords: phsuta,profile,b1ackmonday
Platform: UNKNOWN
Classifier: Development Status :: 3 - Alpha
Classifier: Intended Audience :: Education
Classifier: Topic :: Utilities
Classifier: License :: OSI Approved :: MIT License
Classifier: Programming Language :: Python :: 3
Classifier: Programming Language :: Python :: 3.4
Classifier: Programming Language :: Python :: 3.5
Classifier: Programming Language :: Python :: 3.6
Classifier: Programming Language :: Python :: 3.7
Classifier: Programming Language :: Python :: 3.8
Classifier: Programming Language :: Python :: 3.9
Classifier: Programming Language :: Python :: 3.10
License-File: LICENSE.txt
